[
    {
        "frequenz": 538,
        "gkey": null,
        "layer": 2,
        "leistung": 1.0016,
        "ort": "GAMING Z\u00fcrner",
        "programm": "ORF III Kultur und Information",
        "system": "Fernsehen"
    },
    {
        "frequenz": 92.3,
        "gkey": null,
        "layer": 2,
        "leistung": 0.0501,
        "ort": "GAMING Z\u00fcrner",
        "programm": "\u00d61",
        "system": "H\u00f6rfunk"
    },
    {
        "frequenz": 94.6,
        "gkey": null,
        "layer": 2,
        "leistung": 0.0501,
        "ort": "GAMING Z\u00fcrner",
        "programm": "\u00d62 Nieder\u00f6sterreich",
        "system": "H\u00f6rfunk"
    },
    {
        "frequenz": 95.6,
        "gkey": null,
        "layer": 2,
        "leistung": 0.0501,
        "ort": "GAMING Z\u00fcrner",
        "programm": "\u00d63",
        "system": "H\u00f6rfunk"
    },
    {
        "frequenz": "K 29",
        "gkey": null,
        "layer": 2,
        "leistung": 1.0016,
        "ort": "GAMING Z\u00fcrner",
        "programm": "FM4",
        "system": "Digitaler Rundfunk"
    },
    {
        "frequenz": "K 29",
        "gkey": null,
        "layer": 2,
        "leistung": 1.0016,
        "ort": "GAMING Z\u00fcrner",
        "programm": "\u00d61",
        "system": "Digitaler Rundfunk"
    },
    {
        "frequenz": "K 29",
        "gkey": null,
        "layer": 2,
        "leistung": 1.0016,
        "ort": "GAMING Z\u00fcrner",
        "programm": "\u00d63",
        "system": "Digitaler Rundfunk"
    },
    {
        "frequenz": "K 29",
        "gkey": null,
        "layer": 2,
        "leistung": 1.0016,
        "ort": "GAMING Z\u00fcrner",
        "programm": "ORF 2 (Nieder\u00f6sterreich)",
        "system": "Digitaler Rundfunk"
    },
    {
        "frequenz": "K 29",
        "gkey": null,
        "layer": 2,
        "leistung": 1.0016,
        "ort": "GAMING Z\u00fcrner",
        "programm": "ORF 2 (Ober\u00f6sterreich)",
        "system": "Digitaler Rundfunk"
    },
    {
        "frequenz": "K 29",
        "gkey": null,
        "layer": 2,
        "leistung": 1.0016,
        "ort": "GAMING Z\u00fcrner",
        "programm": "ORF 2 (Salzburg)",
        "system": "Digitaler Rundfunk"
    },
    {
        "frequenz": "K 29",
        "gkey": null,
        "layer": 2,
        "leistung": 1.0016,
        "ort": "GAMING Z\u00fcrner",
        "programm": "ORF eins",
        "system": "Digitaler Rundfunk"
    },
    {
        "frequenz": "K 29",
        "gkey": null,
        "layer": 2,
        "leistung": 1.0016,
        "ort": "GAMING Z\u00fcrner",
        "programm": "ORF III Kultur und Information",
        "system": "Digitaler Rundfunk"
    },
    {
        "frequenz": "K 29",
        "gkey": null,
        "layer": 2,
        "leistung": 1.0016,
        "ort": "GAMING Z\u00fcrner",
        "programm": "ORF Sport Plus",
        "system": "Digitaler Rundfunk"
    }
]