[
    {
        "gkey": "300151",
        "layer": "1",
        "leistung": "307.844231013506",
        "sharing": "1",
        "struktur": "e",
        "system": "GSM/UMTS/LTE"
    },
    {
        "gkey": "300151",
        "layer": "1",
        "leistung": "135",
        "sharing": "1",
        "struktur": "m",
        "system": "GSM/LTE/UMTS"
    },
    {
        "gkey": "300151",
        "layer": "1",
        "leistung": "121.79",
        "sharing": "1",
        "struktur": "f",
        "system": "2G/3G/4G"
    }
]