[
    {
        "gkey": 300724,
        "layer": 1,
        "leistung": 131.5546789524854,
        "sharing": 1,
        "struktur": "d",
        "system": "GSM/UMTS/LTE/5G"
    },
    {
        "gkey": 300724,
        "layer": 1,
        "leistung": 135,
        "sharing": 1,
        "struktur": "d",
        "system": "GSM/UMTS/LTE"
    },
    {
        "gkey": 300724,
        "layer": 1,
        "leistung": 80.13407333943678,
        "sharing": 0,
        "struktur": "d",
        "system": "GSM/UMTS/LTE"
    }
]