[
    {
        "datum": 20220714,
        "datum2": null,
        "datum3": null,
        "davon5g": 0,
        "grenzwert": 0.0095027,
        "grenzwert2": 0,
        "grenzwert3": 0,
        "institut": "Fernmeldeb\u00fcro, Fernmeldebeh\u00f6rde Repuplik \u00d6sterreich",
        "institut2": null,
        "institut3": null,
        "layer": 0,
        "lte": 3.83e-05,
        "lte2": 0,
        "messpunkt": "Schulallee 1, Volksschule/Kindergarten",
        "ort": "Deutsch-Wagram",
        "summe": 0.0007605,
        "summe2": 0,
        "summe3": 0
    }
]